MANIFEST.in
README.md
requirements.txt
setup.py
PJON/.git
PJON/.travis.yml
PJON/LICENSE.md
PJON/README.md
PJON/SECURITY.md
PJON/keywords.txt
PJON/library.json
PJON/library.properties
PJON/.github/FUNDING.yml
PJON/src/PJON.h
PJON/src/PJONDefines.h
PJON/src/PJONDynamicRouter.h
PJON/src/PJONInteractiveRouter.h
PJON/src/PJONRouter.h
PJON/src/PJONSimpleSwitch.h
PJON/src/PJONSwitch.h
PJON/src/PJONVirtualBusRouter.h
PJON/src/interfaces/PJON_Interfaces.h
PJON/src/interfaces/README.md
PJON/src/interfaces/ARDUINO/ESPNOWHelper.h
PJON/src/interfaces/ARDUINO/PJON_ARDUINO_Interface.h
PJON/src/interfaces/ARDUINO/PJON_IO.h
PJON/src/interfaces/ARDUINO/TCPHelper_ARDUINO.h
PJON/src/interfaces/ARDUINO/UDPHelper_ARDUINO.h
PJON/src/interfaces/LINUX/PJON_LINUX_Interface.h
PJON/src/interfaces/LINUX/PJON_LINUX_Interface.inl
PJON/src/interfaces/LINUX/TCPHelper_POSIX.h
PJON/src/interfaces/LINUX/UDPHelper_POSIX.h
PJON/src/interfaces/RPI/PJON_RPI_Interface.h
PJON/src/interfaces/WINX86/PJON_WINX86_Interface.h
PJON/src/interfaces/WINX86/Serial/Serial.cpp
PJON/src/interfaces/WINX86/Serial/Serial.h
PJON/src/strategies/PJON_Strategies.h
PJON/src/strategies/README.md
PJON/src/strategies/AnalogSampling/AnalogSampling.h
PJON/src/strategies/AnalogSampling/README.md
PJON/src/strategies/AnalogSampling/Timing.h
PJON/src/strategies/AnalogSampling/documentation/LED-selection.md
PJON/src/strategies/AnalogSampling/images/AnalogSampling_PJDLS_Bad_LED.jpg
PJON/src/strategies/AnalogSampling/images/AnalogSampling_PJDLS_Good_LED.jpg
PJON/src/strategies/AnalogSampling/images/AnalogSampling_PJDLS_LED_Transceiver.jpg
PJON/src/strategies/AnalogSampling/specification/PJDLS-specification-v2.0.md
PJON/src/strategies/AnalogSampling/specification/obsolete/PJDLS-specification-v1.0.md
PJON/src/strategies/Any/Any.h
PJON/src/strategies/Any/README.md
PJON/src/strategies/Any/StrategyLink.h
PJON/src/strategies/Any/StrategyLinkBase.h
PJON/src/strategies/DualUDP/DualUDP.h
PJON/src/strategies/DualUDP/README.md
pjon_cython.egg-info/PKG-INFO
pjon_cython.egg-info/SOURCES.txt
pjon_cython.egg-info/dependency_links.txt
pjon_cython.egg-info/top_level.txt
