Metadata-Version: 2.1
Name: pjon-cython
Version: 12.0.0
Summary: Call the PJON C++ library directly from Python
Home-page: https://github.com/xlfe/PJON-cython
Author: xlfe
License: Apache 2.0
Platform: UNKNOWN
Classifier: Programming Language :: Python :: 2.7
Classifier: Programming Language :: Python :: 3.4
Classifier: Programming Language :: Python :: 3.5
Classifier: Programming Language :: Python :: 3.6
Classifier: Programming Language :: Python :: 3.7
